example/__init__.py
example/__main__.py
example/model.py
objectbox/__init__.py
objectbox/box.py
objectbox/builder.py
objectbox/c.py
objectbox/condition.py
objectbox/objectbox.py
objectbox/query.py
objectbox/query_builder.py
objectbox/transaction.py
objectbox/version.py
objectbox/lib/AMD64/objectbox.dll
objectbox/lib/aarch64/libobjectbox.so
objectbox/lib/armv6l/libobjectbox.so
objectbox/lib/armv7l/libobjectbox.so
objectbox/lib/macos-universal/libobjectbox.dylib
objectbox/lib/x86_64/libobjectbox.so
objectbox/model/__init__.py
objectbox/model/entity.py
objectbox/model/model.py
objectbox/model/properties.py
objectbox-0.6.1.dist-info/LICENSE
objectbox-0.6.1.dist-info/METADATA
objectbox-0.6.1.dist-info/WHEEL
objectbox-0.6.1.dist-info/top_level.txt
objectbox-0.6.1.dist-info/RECORD
