Metadata-Version: 2.1
Name: objectbox
Version: 0.6.1
Summary: ObjectBox is a superfast lightweight database for objects
Home-page: https://objectbox.io
Author: ObjectBox
License: Apache 2.0
Project-URL: GitHub, https://github.com/objectbox/objectbox-python
Project-URL: Tracker, https://github.com/objectbox/objectbox-python/issues
Classifier: Development Status :: 3 - Alpha
Classifier: Programming Language :: Python :: 3
Classifier: Programming Language :: Python :: 3.4
Classifier: Programming Language :: Python :: 3.5
Classifier: Programming Language :: Python :: 3.6
Classifier: Programming Language :: Python :: 3.7
Classifier: Programming Language :: Python :: 3.8
Classifier: Programming Language :: Python :: 3.9
Classifier: Programming Language :: Python :: 3.10
Classifier: Programming Language :: Python :: 3.11
Classifier: Programming Language :: Python :: 3.12
Classifier: Programming Language :: C
Classifier: Programming Language :: C++
Classifier: Operating System :: POSIX :: Linux
Classifier: Operating System :: MacOS
Classifier: Operating System :: Microsoft :: Windows
Classifier: Topic :: Database
Classifier: Topic :: Database :: Database Engines/Servers
Classifier: Topic :: Database :: Front-Ends
Classifier: Topic :: Software Development
Classifier: Topic :: Software Development :: Libraries
Classifier: License :: OSI Approved :: Apache Software License
Classifier: Intended Audience :: Developers
Requires-Python: >=3.4, <4
License-File: LICENSE
Requires-Dist: flatbuffers ==23.5.26
Requires-Dist: numpy
